{".class": "MypyFile", "_fullname": "pyspark.pandas.mlflow", "future_import_flags": [], "is_partial_stub_package": false, "is_stub": false, "names": {".class": "SymbolTable", "Any": {".class": "SymbolTableNode", "cross_ref": "typing.Any", "kind": "Gdef", "module_public": false}, "DataFrame": {".class": "SymbolTableNode", "cross_ref": "pyspark.pandas.frame.DataFrame", "kind": "Gdef", "module_public": false}, "DataType": {".class": "SymbolTableNode", "cross_ref": "pyspark.sql.types.DataType", "kind": "Gdef", "module_public": false}, "Dtype": {".class": "SymbolTableNode", "cross_ref": "pyspark.pandas._typing.Dtype", "kind": "Gdef", "module_public": false}, "Label": {".class": "SymbolTableNode", "cross_ref": "pyspark.pandas._typing.Label", "kind": "Gdef", "module_public": false}, "List": {".class": "SymbolTableNode", "cross_ref": "typing.List", "kind": "Gdef", "module_public": false}, "PythonModelWrapper": {".class": "SymbolTableNode", "kind": "Gdef", "node": {".class": "TypeInfo", "_promote": [], "abstract_attributes": [], "bases": ["builtins.object"], "declared_metaclass": null, "defn": {".class": "ClassDef", "fullname": "pyspark.pandas.mlflow.PythonModelWrapper", "name": "PythonModelWrapper", "type_vars": []}, "deletable_attributes": [], "flags": [], "fullname": "pyspark.pandas.mlflow.PythonModelWrapper", "has_param_spec_type": false, "metaclass_type": null, "metadata": {}, "module_name": "pyspark.pandas.mlflow", "mro": ["pyspark.pandas.mlflow.PythonModelWrapper", "builtins.object"], "names": {".class": "SymbolTable", "__init__": {".class": "SymbolTableNode", "kind": "Mdef", "node": {".class": "FuncDef", "abstract_status": 0, "arg_kinds": [0, 0, 0], "arg_names": ["self", "model_uri", "return_type_hint"], "flags": [], "fullname": "pyspark.pandas.mlflow.PythonModelWrapper.__init__", "name": "__init__", "type": {".class": "CallableType", "arg_kinds": [0, 0, 0], "arg_names": ["self", "model_uri", "return_type_hint"], "arg_types": ["pyspark.pandas.mlflow.PythonModelWrapper", "builtins.str", {".class": "UnionType", "items": ["builtins.str", "builtins.type", {".class": "TypeAliasType", "args": [], "type_ref": "pyspark.pandas._typing.Dtype"}]}], "bound_args": [], "def_extras": {"first_arg": "self"}, "fallback": "builtins.function", "from_concatenate": false, "implicit": false, "is_ellipsis_args": false, "name": "__init__ of PythonModelWrapper", "ret_type": {".class": "NoneType"}, "type_guard": null, "unpack_kwargs": false, "variables": []}}}, "__repr__": {".class": "SymbolTableNode", "kind": "Mdef", "node": {".class": "FuncDef", "abstract_status": 0, "arg_kinds": [0], "arg_names": [null], "flags": [], "fullname": "pyspark.pandas.mlflow.PythonModelWrapper.__repr__", "name": "__repr__", "type": {".class": "CallableType", "arg_kinds": [0], "arg_names": [null], "arg_types": ["pyspark.pandas.mlflow.PythonModelWrapper"], "bound_args": [], "def_extras": {"first_arg": "self"}, "fallback": "builtins.function", "from_concatenate": false, "implicit": false, "is_ellipsis_args": false, "name": "__repr__ of PythonModelWrapper", "ret_type": "builtins.str", "type_guard": null, "unpack_kwargs": false, "variables": []}}}, "__str__": {".class": "SymbolTableNode", "kind": "Mdef", "node": {".class": "FuncDef", "abstract_status": 0, "arg_kinds": [0], "arg_names": [null], "flags": [], "fullname": "pyspark.pandas.mlflow.PythonModelWrapper.__str__", "name": "__str__", "type": {".class": "CallableType", "arg_kinds": [0], "arg_names": [null], "arg_types": ["pyspark.pandas.mlflow.PythonModelWrapper"], "bound_args": [], "def_extras": {"first_arg": "self"}, "fallback": "builtins.function", "from_concatenate": false, "implicit": false, "is_ellipsis_args": false, "name": "__str__ of PythonModelWrapper", "ret_type": "builtins.str", "type_guard": null, "unpack_kwargs": false, "variables": []}}}, "_model": {".class": "SymbolTableNode", "kind": "Mdef", "node": {".class": "Decorator", "func": {".class": "FuncDef", "abstract_status": 0, "arg_kinds": [0], "arg_names": ["self"], "flags": ["is_decorated"], "fullname": "pyspark.pandas.mlflow.PythonModelWrapper._model", "name": "_model", "type": {".class": "CallableType", "arg_kinds": [0], "arg_names": ["self"], "arg_types": ["pyspark.pandas.mlflow.PythonModelWrapper"], "bound_args": [], "def_extras": {"first_arg": "self"}, "fallback": "builtins.function", "from_concatenate": false, "implicit": false, "is_ellipsis_args": false, "name": "_model of PythonModelWrapper", "ret_type": {".class": "AnyType", "missing_import_name": null, "source_any": null, "type_of_any": 2}, "type_guard": null, "unpack_kwargs": false, "variables": []}}, "is_overload": false, "var": {".class": "Var", "flags": ["is_initialized_in_class", "is_ready", "is_inferred"], "fullname": "pyspark.pandas.mlflow.PythonModelWrapper._model", "name": "_model", "type": {".class": "AnyType", "missing_import_name": null, "source_any": {".class": "AnyType", "missing_import_name": null, "source_any": null, "type_of_any": 6}, "type_of_any": 7}}}}, "_model_udf": {".class": "SymbolTableNode", "kind": "Mdef", "node": {".class": "Decorator", "func": {".class": "FuncDef", "abstract_status": 0, "arg_kinds": [0], "arg_names": ["self"], "flags": ["is_decorated"], "fullname": "pyspark.pandas.mlflow.PythonModelWrapper._model_udf", "name": "_model_udf", "type": {".class": "CallableType", "arg_kinds": [0], "arg_names": ["self"], "arg_types": ["pyspark.pandas.mlflow.PythonModelWrapper"], "bound_args": [], "def_extras": {"first_arg": "self"}, "fallback": "builtins.function", "from_concatenate": false, "implicit": false, "is_ellipsis_args": false, "name": "_model_udf of PythonModelWrapper", "ret_type": {".class": "AnyType", "missing_import_name": null, "source_any": null, "type_of_any": 2}, "type_guard": null, "unpack_kwargs": false, "variables": []}}, "is_overload": false, "var": {".class": "Var", "flags": ["is_initialized_in_class", "is_ready", "is_inferred"], "fullname": "pyspark.pandas.mlflow.PythonModelWrapper._model_udf", "name": "_model_udf", "type": {".class": "AnyType", "missing_import_name": null, "source_any": {".class": "AnyType", "missing_import_name": null, "source_any": null, "type_of_any": 6}, "type_of_any": 7}}}}, "_model_uri": {".class": "SymbolTableNode", "implicit": true, "kind": "Mdef", "node": {".class": "Var", "flags": ["is_inferred"], "fullname": "pyspark.pandas.mlflow.PythonModelWrapper._model_uri", "name": "_model_uri", "type": "builtins.str"}}, "_return_type": {".class": "SymbolTableNode", "kind": "Mdef", "node": {".class": "Decorator", "func": {".class": "FuncDef", "abstract_status": 0, "arg_kinds": [0], "arg_names": ["self"], "flags": ["is_decorated"], "fullname": "pyspark.pandas.mlflow.PythonModelWrapper._return_type", "name": "_return_type", "type": {".class": "CallableType", "arg_kinds": [0], "arg_names": ["self"], "arg_types": ["pyspark.pandas.mlflow.PythonModelWrapper"], "bound_args": [], "def_extras": {"first_arg": "self"}, "fallback": "builtins.function", "from_concatenate": false, "implicit": false, "is_ellipsis_args": false, "name": "_return_type of PythonModelWrapper", "ret_type": "pyspark.sql.types.DataType", "type_guard": null, "unpack_kwargs": false, "variables": []}}, "is_overload": false, "var": {".class": "Var", "flags": ["is_initialized_in_class", "is_ready", "is_inferred"], "fullname": "pyspark.pandas.mlflow.PythonModelWrapper._return_type", "name": "_return_type", "type": {".class": "AnyType", "missing_import_name": null, "source_any": {".class": "AnyType", "missing_import_name": null, "source_any": null, "type_of_any": 6}, "type_of_any": 7}}}}, "_return_type_hint": {".class": "SymbolTableNode", "implicit": true, "kind": "Mdef", "node": {".class": "Var", "flags": ["is_inferred"], "fullname": "pyspark.pandas.mlflow.PythonModelWrapper._return_type_hint", "name": "_return_type_hint", "type": {".class": "UnionType", "items": ["builtins.str", "builtins.type", {".class": "TypeAliasType", "args": [], "type_ref": "pyspark.pandas._typing.Dtype"}]}}}, "predict": {".class": "SymbolTableNode", "kind": "Mdef", "node": {".class": "FuncDef", "abstract_status": 0, "arg_kinds": [0, 0], "arg_names": ["self", "data"], "flags": [], "fullname": "pyspark.pandas.mlflow.PythonModelWrapper.predict", "name": "predict", "type": {".class": "CallableType", "arg_kinds": [0, 0], "arg_names": ["self", "data"], "arg_types": ["pyspark.pandas.mlflow.PythonModelWrapper", {".class": "UnionType", "items": [{".class": "Instance", "args": [{".class": "AnyType", "missing_import_name": null, "source_any": null, "type_of_any": 4}], "type_ref": "pyspark.pandas.frame.DataFrame"}, {".class": "AnyType", "missing_import_name": "pyspark.pandas.mlflow.pd", "source_any": null, "type_of_any": 3}]}], "bound_args": [], "def_extras": {"first_arg": "self"}, "fallback": "builtins.function", "from_concatenate": false, "implicit": false, "is_ellipsis_args": false, "name": "predict of PythonModelWrapper", "ret_type": {".class": "UnionType", "items": [{".class": "Instance", "args": [{".class": "AnyType", "missing_import_name": null, "source_any": null, "type_of_any": 4}], "type_ref": "pyspark.pandas.series.Series"}, {".class": "AnyType", "missing_import_name": "pyspark.pandas.mlflow.pd", "source_any": null, "type_of_any": 3}]}, "type_guard": null, "unpack_kwargs": false, "variables": []}}}}, "slots": null, "tuple_type": null, "type_vars": [], "typeddict_type": null}}, "Series": {".class": "SymbolTableNode", "cross_ref": "pyspark.pandas.series.Series", "kind": "Gdef", "module_public": false}, "Union": {".class": "SymbolTableNode", "cross_ref": "typing.Union", "kind": "Gdef", "module_public": false}, "__all__": {".class": "SymbolTableNode", "kind": "Gdef", "module_public": false, "node": {".class": "Var", "flags": ["is_inferred", "has_explicit_value"], "fullname": "pyspark.pandas.mlflow.__all__", "name": "__all__", "type": {".class": "Instance", "args": ["builtins.str"], "type_ref": "builtins.list"}}}, "__annotations__": {".class": "SymbolTableNode", "kind": "Gdef", "module_public": false, "node": {".class": "Var", "flags": ["is_ready"], "fullname": "pyspark.pandas.mlflow.__annotations__", "name": "__annotations__", "type": {".class": "Instance", "args": ["builtins.str", {".class": "AnyType", "missing_import_name": null, "source_any": null, "type_of_any": 6}], "type_ref": "builtins.dict"}}}, "__doc__": {".class": "SymbolTableNode", "kind": "Gdef", "module_public": false, "node": {".class": "Var", "flags": ["is_ready"], "fullname": "pyspark.pandas.mlflow.__doc__", "name": "__doc__", "type": "builtins.str"}}, "__file__": {".class": "SymbolTableNode", "kind": "Gdef", "module_public": false, "node": {".class": "Var", "flags": ["is_ready"], "fullname": "pyspark.pandas.mlflow.__file__", "name": "__file__", "type": "builtins.str"}}, "__name__": {".class": "SymbolTableNode", "kind": "Gdef", "module_public": false, "node": {".class": "Var", "flags": ["is_ready"], "fullname": "pyspark.pandas.mlflow.__name__", "name": "__name__", "type": "builtins.str"}}, "__package__": {".class": "SymbolTableNode", "kind": "Gdef", "module_public": false, "node": {".class": "Var", "flags": ["is_ready"], "fullname": "pyspark.pandas.mlflow.__package__", "name": "__package__", "type": "builtins.str"}}, "_test": {".class": "SymbolTableNode", "kind": "Gdef", "module_public": false, "node": {".class": "FuncDef", "abstract_status": 0, "arg_kinds": [], "arg_names": [], "flags": [], "fullname": "pyspark.pandas.mlflow._test", "name": "_test", "type": {".class": "CallableType", "arg_kinds": [], "arg_names": [], "arg_types": [], "bound_args": [], "def_extras": {"first_arg": null}, "fallback": "builtins.function", "from_concatenate": false, "implicit": false, "is_ellipsis_args": false, "name": "_test", "ret_type": {".class": "NoneType"}, "type_guard": null, "unpack_kwargs": false, "variables": []}}}, "as_spark_type": {".class": "SymbolTableNode", "cross_ref": "pyspark.pandas.typedef.typehints.as_spark_type", "kind": "Gdef", "module_public": false}, "default_session": {".class": "SymbolTableNode", "cross_ref": "pyspark.pandas.utils.default_session", "kind": "Gdef", "module_public": false}, "first_series": {".class": "SymbolTableNode", "cross_ref": "pyspark.pandas.series.first_series", "kind": "Gdef", "module_public": false}, "lazy_property": {".class": "SymbolTableNode", "cross_ref": "pyspark.pandas.utils.lazy_property", "kind": "Gdef", "module_public": false}, "load_model": {".class": "SymbolTableNode", "kind": "Gdef", "node": {".class": "FuncDef", "abstract_status": 0, "arg_kinds": [0, 1], "arg_names": ["model_uri", "predict_type"], "flags": [], "fullname": "pyspark.pandas.mlflow.load_model", "name": "load_model", "type": {".class": "CallableType", "arg_kinds": [0, 1], "arg_names": ["model_uri", "predict_type"], "arg_types": ["builtins.str", {".class": "UnionType", "items": ["builtins.str", "builtins.type", {".class": "TypeAliasType", "args": [], "type_ref": "pyspark.pandas._typing.Dtype"}]}], "bound_args": [], "def_extras": {"first_arg": null}, "fallback": "builtins.function", "from_concatenate": false, "implicit": false, "is_ellipsis_args": false, "name": "load_model", "ret_type": "pyspark.pandas.mlflow.PythonModelWrapper", "type_guard": null, "unpack_kwargs": false, "variables": []}}}, "mlflow": {".class": "SymbolTableNode", "kind": "Gdef", "module_public": false, "node": {".class": "Var", "flags": ["is_suppressed_import", "is_ready", "is_inferred"], "fullname": "pyspark.pandas.mlflow.mlflow", "name": "mlflow", "type": {".class": "AnyType", "missing_import_name": "pyspark.pandas.mlflow.mlflow", "source_any": null, "type_of_any": 3}}}, "np": {".class": "SymbolTableNode", "cross_ref": "numpy", "kind": "Gdef", "module_public": false}, "pd": {".class": "SymbolTableNode", "kind": "Gdef", "module_public": false, "node": {".class": "Var", "flags": ["is_suppressed_import", "is_ready", "is_inferred"], "fullname": "pyspark.pandas.mlflow.pd", "name": "pd", "type": {".class": "AnyType", "missing_import_name": "pyspark.pandas.mlflow.pd", "source_any": null, "type_of_any": 3}}}, "sklearn": {".class": "SymbolTableNode", "kind": "Gdef", "module_public": false, "node": {".class": "Var", "flags": ["is_suppressed_import", "is_ready", "is_inferred"], "fullname": "pyspark.pandas.mlflow.sklearn", "name": "sklearn", "type": {".class": "AnyType", "missing_import_name": "pyspark.pandas.mlflow.sklearn", "source_any": null, "type_of_any": 3}}}}, "path": "C:\\Users\\Egor\\AppData\\Local\\Programs\\Python\\Python310\\lib\\site-packages\\pyspark\\pandas\\mlflow.py"}